myjive/__init__.py
myjive/declare.py
myjive/app/__init__.py
myjive/app/initmodule.py
myjive/app/main.py
myjive/app/module.py
myjive/app/outputmodule.py
myjive/fem/__init__.py
myjive/fem/dofspace.py
myjive/fem/elementgroup.py
myjive/fem/elementset.py
myjive/fem/groupset.py
myjive/fem/itemgroup.py
myjive/fem/itemset.py
myjive/fem/nodegroup.py
myjive/fem/nodeset.py
myjive/fem/paramshapes.py
myjive/fem/pointset.py
myjive/fem/shape.py
myjive/implicit/__init__.py
myjive/implicit/linsolvemodule.py
myjive/implicit/solvermodule.py
myjive/model/__init__.py
myjive/model/model.py
myjive/names/__init__.py
myjive/names/globnames.py
myjive/solver/__init__.py
myjive/solver/cgsolver.py
myjive/solver/cholmodsolver.py
myjive/solver/constrainer.py
myjive/solver/constraints.py
myjive/solver/diagprecon.py
myjive/solver/directsolver.py
myjive/solver/icholprecon.py
myjive/solver/idprecon.py
myjive/solver/iterativesolver.py
myjive/solver/preconditioner.py
myjive/solver/solver.py
myjive/solver/sparsecholeskysolver.py
myjive/solver/jit/__init__.py
myjive/solver/jit/cholesky.py
myjive/solver/jit/spsolve.py
myjive/solver/jit/sputil.py
myjive/solver/util/__init__.py
myjive/solver/util/reorder.py
myjive/util/__init__.py
myjive/util/proputils.py
myjive/util/saveconfig.py
myjive/util/table.py
myjive/util/xtable.py
myjive/util/jit/__init__.py
myjive/util/jit/xtable.py
myjive-0.1.14.dist-info/licenses/LICENSE.txt
myjivex/__init__.py
myjivex/declare.py
myjivex/materials/__init__.py
myjivex/materials/deterioratedmaterial.py
myjivex/materials/heterogeneousmaterial.py
myjivex/materials/isotropicmaterial.py
myjivex/materials/material.py
myjivex/materials/newmaterial.py
myjivex/models/__init__.py
myjivex/models/barmodel.py
myjivex/models/dirimodel.py
myjivex/models/elasticmodel.py
myjivex/models/loadmodel.py
myjivex/models/neumannmodel.py
myjivex/models/poissonmodel.py
myjivex/models/solidmodel.py
myjivex/models/timoshenkomodel.py
myjivex/modules/__init__.py
myjivex/modules/viewmodule.py
myjivex/modules/vtkoutmodule.py
myjivex/util/__init__.py
myjive-0.1.14.dist-info/METADATA
myjive-0.1.14.dist-info/WHEEL
myjive-0.1.14.dist-info/top_level.txt
myjive-0.1.14.dist-info/RECORD
