Metadata-Version: 2.4
Name: myjive
Version: 0.1.14
Summary: Personal implementation of jive C++ library in Python
Author-email: Anne Poot <a.poot-1@tudelft.nl>
License: Copyright (c) 2024 Anne Poot
Project-URL: homepage, https://gitlab.tudelft.nl/apoot1/myjive
Project-URL: download, https://gitlab.tudelft.nl/apoot1/myjive/-/archive/v0.1.14/myjive-v0.1.14.tar.gz
Keywords: jive,mathematics,finite-element-method,engineering
Classifier: Development Status :: 3 - Alpha
Classifier: Intended Audience :: Developers
Classifier: Topic :: Scientific/Engineering :: Mathematics
Classifier: Programming Language :: Python :: 3.10
Requires-Python: ==3.10.*
License-File: LICENSE.txt
Requires-Dist: matplotlib
Requires-Dist: numba
Requires-Dist: numpy<2.0.0
Requires-Dist: pandas
Requires-Dist: scikit-sparse>=0.4.12
Requires-Dist: scipy>=1.12
Provides-Extra: dev
Requires-Dist: pytest; extra == "dev"
Dynamic: license-file
